Metadata-Version: 1.0
Name: neural-networks-tfw1
Version: 0.1
Summary: Implementing Neural Networks with Tensorflow
Home-page: UNKNOWN
Author: Dilay Fidan Ercelik
Author-email: dilay.ercelik@gmail.com
License: UNKNOWN
Platform: UNKNOWN
